datasets/__init__.py
datasets/build_imagenet_data.py
datasets/build_visualwakewords_data.py
datasets/build_visualwakewords_data_lib.py
datasets/cifar10.py
datasets/dataset_factory.py
datasets/dataset_utils.py
datasets/download_and_convert_cifar10.py
datasets/download_and_convert_flowers.py
datasets/download_and_convert_mnist.py
datasets/flowers.py
datasets/imagenet.py
datasets/mnist.py
datasets/preprocess_imagenet_validation_data.py
datasets/process_bounding_boxes.py
datasets/visualwakewords.py
deployment/__init__.py
deployment/model_deploy.py
deployment/model_deploy_test.py
nets/__init__.py
nets/alexnet.py
nets/alexnet_test.py
nets/cifarnet.py
nets/cyclegan.py
nets/cyclegan_test.py
nets/dcgan.py
nets/dcgan_test.py
nets/i3d.py
nets/i3d_test.py
nets/i3d_utils.py
nets/inception.py
nets/inception_resnet_v2.py
nets/inception_resnet_v2_test.py
nets/inception_utils.py
nets/inception_v1.py
nets/inception_v1_test.py
nets/inception_v2.py
nets/inception_v2_test.py
nets/inception_v3.py
nets/inception_v3_test.py
nets/inception_v4.py
nets/inception_v4_test.py
nets/lenet.py
nets/mobilenet_v1.py
nets/mobilenet_v1_eval.py
nets/mobilenet_v1_test.py
nets/mobilenet_v1_train.py
nets/nets_factory.py
nets/nets_factory_test.py
nets/overfeat.py
nets/overfeat_test.py
nets/pix2pix.py
nets/pix2pix_test.py
nets/resnet_utils.py
nets/resnet_v1.py
nets/resnet_v1_test.py
nets/resnet_v2.py
nets/resnet_v2_test.py
nets/s3dg.py
nets/s3dg_test.py
nets/vgg.py
nets/vgg_test.py
nets/mobilenet/__init__.py
nets/mobilenet/conv_blocks.py
nets/mobilenet/mobilenet.py
nets/mobilenet/mobilenet_v2.py
nets/mobilenet/mobilenet_v2_test.py
nets/nasnet/__init__.py
nets/nasnet/nasnet.py
nets/nasnet/nasnet_test.py
nets/nasnet/nasnet_utils.py
nets/nasnet/nasnet_utils_test.py
nets/nasnet/pnasnet.py
nets/nasnet/pnasnet_test.py
object_detection/__init__.py
object_detection/eval_util.py
object_detection/eval_util_test.py
object_detection/export_inference_graph.py
object_detection/export_tflite_ssd_graph.py
tf_object_detection-0.0.3.dist-info/LICENSE
tf_object_detection-0.0.3.dist-info/METADATA
tf_object_detection-0.0.3.dist-info/WHEEL
tf_object_detection-0.0.3.dist-info/top_level.txt
tf_object_detection-0.0.3.dist-info/RECORD
