Metadata-Version: 2.1
Name: tf-object-detection
Version: 0.0.3
Summary: A Thin Wrapper around Tensorflow Object Detection API for Easy Installation and Use
Home-page: https://github.com/junjuew/tf_object_detection
Author: Junjue Wang
Author-email: junjuew@cs.cmu.edu
License: Apache License 2.0
Platform: UNKNOWN
Classifier: Programming Language :: Python :: 3.6
Classifier: Programming Language :: Python :: 3.7
Classifier: Topic :: Scientific/Engineering :: Artificial Intelligence
Classifier: Intended Audience :: Developers
Classifier: Intended Audience :: Science/Research
Requires-Python: >3.5, <4
Requires-Dist: setuptools (>=41.0.0)
Requires-Dist: tensorflow-gpu (<2.0)
Requires-Dist: cython
Requires-Dist: contextlib2
Requires-Dist: pillow
Requires-Dist: lxml
Requires-Dist: pycocotools-fix
Requires-Dist: jupyter
Requires-Dist: matplotlib
